tasklauncher/__init__.py
tasklauncher/core.py
tasklauncher/process_manager.py
tasklauncher/utils.py
tests/__init__.py
tests/example.py
tests/test_launcher.py
TaskLauncher-0.1.0.dist-info/LICENSE
TaskLauncher-0.1.0.dist-info/METADATA
TaskLauncher-0.1.0.dist-info/WHEEL
TaskLauncher-0.1.0.dist-info/top_level.txt
TaskLauncher-0.1.0.dist-info/RECORD
