Metadata-Version: 2.1
Name: TaskLauncher
Version: 0.1.0
Summary: A cross-platform command and python script task launcher with process management.
Home-page: https://github.com/zeturns/TaskLauncher
Author: Zeturn
Author-email: hollowdata@outlook.com
Requires-Python: >=3.7
License-File: LICENSE
Requires-Dist: psutil
